primeintellect/__init__.py
primeintellect/main.py
primeintellect-0.0.0.dist-info/LICENSE
primeintellect-0.0.0.dist-info/METADATA
primeintellect-0.0.0.dist-info/WHEEL
primeintellect-0.0.0.dist-info/top_level.txt
primeintellect-0.0.0.dist-info/RECORD
