Metadata-Version: 2.1
Name: primeintellect
Version: 0.0.0
Summary: primeintellect package
Home-page: https://github.com/PrimeIntellect-ai/primeintellect
Author: Jack Min Ong
Author-email: jackmin@primeintellect.ai
Classifier: Programming Language :: Python :: 3
Classifier: License :: OSI Approved :: MIT License
Classifier: Operating System :: OS Independent
Requires-Python: >=3.8
License-File: LICENSE
